[{"authorTime":"2019-12-22 02:01:10","codes":[{"authorDate":"2019-12-19 03:41:09","commitOrder":2,"curCode":"    protected boolean validateTaskParameters(DBTTask task, MySQLExportSettings settings, Log log) {\n        if (task.getType().getId().equals(MySQLTasks.TASK_DATABASE_BACKUP)) {\n            final File dir = settings.getOutputFolder();\n            if (!dir.exists()) {\n                if (!dir.mkdirs()) {\n                    log.error(\"Can't create directory '\" + dir.getAbsolutePath() + \"'\");\n                    return false;\n                }\n            }\n        }\n        return true;\n    }\n","date":"2019-12-19 03:41:09","endLine":50,"groupId":"7627","id":1,"instanceNumber":1,"isCurCommit":0,"methodName":"validateTaskParameters","params":"(DBTTasktask@MySQLExportSettingssettings@Loglog)","path":"/mnt/clonedata/CloneManagementServer/ManagementServer/consistResult/result-dbeaver-10-0.7/blobInfo/CC_OUT/blobs/9d/80acaad44c43384ffb5e1083804309393ad720.src","preCode":"    protected boolean validateTaskParameters(DBTTask task, MySQLExportSettings settings, Log log) {\n        if (task.getType().getId().equals(MySQLTasks.TASK_DATABASE_BACKUP)) {\n            final File dir = settings.getOutputFolder();\n            if (!dir.exists()) {\n                if (!dir.mkdirs()) {\n                    log.error(\"Can't create directory '\" + dir.getAbsolutePath() + \"'\");\n                    return false;\n                }\n            }\n        }\n        return true;\n    }\n","realPath":"plugins/org.jkiss.dbeaver.ext.mysql/src/org/jkiss/dbeaver/ext/mysql/tasks/MySQLDatabaseExportHandler.java","repoName":"dbeaver","snippetEndLine":0,"snippetStartLine":0,"startLine":39,"status":"NB"},{"authorDate":"2019-12-22 02:01:10","commitOrder":2,"curCode":"    protected boolean validateTaskParameters(DBTTask task, PostgreBackupSettings settings, Log log) {\n        if (task.getType().getId().equals(PostgreSQLTasks.TASK_DATABASE_BACKUP)) {\n            final File dir = settings.getOutputFolder();\n            if (!dir.exists()) {\n                if (!dir.mkdirs()) {\n                    log.error(\"Can't create directory '\" + dir.getAbsolutePath() + \"'\");\n                    return false;\n                }\n            }\n        }\n        return true;\n    }\n","date":"2019-12-22 02:01:10","endLine":48,"groupId":"7627","id":2,"instanceNumber":2,"isCurCommit":0,"methodName":"validateTaskParameters","params":"(DBTTasktask@PostgreBackupSettingssettings@Loglog)","path":"/mnt/clonedata/CloneManagementServer/ManagementServer/consistResult/result-dbeaver-10-0.7/blobInfo/CC_OUT/blobs/52/3211695c776f95515fc4285a32a13ba052a9ab.src","preCode":"    protected boolean validateTaskParameters(DBTTask task, PostgreBackupSettings settings, Log log) {\n        if (task.getType().getId().equals(PostgreSQLTasks.TASK_DATABASE_BACKUP)) {\n            final File dir = settings.getOutputFolder();\n            if (!dir.exists()) {\n                if (!dir.mkdirs()) {\n                    log.error(\"Can't create directory '\" + dir.getAbsolutePath() + \"'\");\n                    return false;\n                }\n            }\n        }\n        return true;\n    }\n","realPath":"plugins/org.jkiss.dbeaver.ext.postgresql/src/org/jkiss/dbeaver/ext/postgresql/tasks/PostgreDatabaseBackupHandler.java","repoName":"dbeaver","snippetEndLine":0,"snippetStartLine":0,"startLine":37,"status":"B"}],"commitId":"bb9fd77daf267eb315761d430c166d601b82971b","commitMessage":"@@@#7444 PG tasks. MySQL and PG settings load/save fixes\n\n\nFormer-commit-id: 2f064417fa6640e4d73ce0e459951eb23a60e6dd","date":"2019-12-22 02:01:10","modifiedFileCount":"22","status":"M","submitter":"Serge Rider"},{"authorTime":"2019-12-22 03:28:45","codes":[{"authorDate":"2019-12-19 03:41:09","commitOrder":3,"curCode":"    protected boolean validateTaskParameters(DBTTask task, MySQLExportSettings settings, Log log) {\n        if (task.getType().getId().equals(MySQLTasks.TASK_DATABASE_BACKUP)) {\n            final File dir = settings.getOutputFolder();\n            if (!dir.exists()) {\n                if (!dir.mkdirs()) {\n                    log.error(\"Can't create directory '\" + dir.getAbsolutePath() + \"'\");\n                    return false;\n                }\n            }\n        }\n        return true;\n    }\n","date":"2019-12-19 03:41:09","endLine":50,"groupId":"10158","id":3,"instanceNumber":1,"isCurCommit":0,"methodName":"validateTaskParameters","params":"(DBTTasktask@MySQLExportSettingssettings@Loglog)","path":"/mnt/clonedata/CloneManagementServer/ManagementServer/consistResult/result-dbeaver-10-0.7/blobInfo/CC_OUT/blobs/9d/80acaad44c43384ffb5e1083804309393ad720.src","preCode":"    protected boolean validateTaskParameters(DBTTask task, MySQLExportSettings settings, Log log) {\n        if (task.getType().getId().equals(MySQLTasks.TASK_DATABASE_BACKUP)) {\n            final File dir = settings.getOutputFolder();\n            if (!dir.exists()) {\n                if (!dir.mkdirs()) {\n                    log.error(\"Can't create directory '\" + dir.getAbsolutePath() + \"'\");\n                    return false;\n                }\n            }\n        }\n        return true;\n    }\n","realPath":"plugins/org.jkiss.dbeaver.ext.mysql/src/org/jkiss/dbeaver/ext/mysql/tasks/MySQLDatabaseExportHandler.java","repoName":"dbeaver","snippetEndLine":0,"snippetStartLine":0,"startLine":39,"status":"N"},{"authorDate":"2019-12-22 03:28:45","commitOrder":3,"curCode":"    protected boolean validateTaskParameters(DBTTask task, PostgreDatabaseBackupSettings settings, Log log) {\n        if (task.getType().getId().equals(PostgreSQLTasks.TASK_DATABASE_BACKUP)) {\n            final File dir = settings.getOutputFolder();\n            if (!dir.exists()) {\n                if (!dir.mkdirs()) {\n                    log.error(\"Can't create directory '\" + dir.getAbsolutePath() + \"'\");\n                    return false;\n                }\n            }\n        }\n        return true;\n    }\n","date":"2019-12-22 03:28:45","endLine":48,"groupId":"10158","id":4,"instanceNumber":2,"isCurCommit":0,"methodName":"validateTaskParameters","params":"(DBTTasktask@PostgreDatabaseBackupSettingssettings@Loglog)","path":"/mnt/clonedata/CloneManagementServer/ManagementServer/consistResult/result-dbeaver-10-0.7/blobInfo/CC_OUT/blobs/38/2c4b93aa27c7fe66d7b0da52621c3f57223145.src","preCode":"    protected boolean validateTaskParameters(DBTTask task, PostgreBackupSettings settings, Log log) {\n        if (task.getType().getId().equals(PostgreSQLTasks.TASK_DATABASE_BACKUP)) {\n            final File dir = settings.getOutputFolder();\n            if (!dir.exists()) {\n                if (!dir.mkdirs()) {\n                    log.error(\"Can't create directory '\" + dir.getAbsolutePath() + \"'\");\n                    return false;\n                }\n            }\n        }\n        return true;\n    }\n","realPath":"plugins/org.jkiss.dbeaver.ext.postgresql/src/org/jkiss/dbeaver/ext/postgresql/tasks/PostgreDatabaseBackupHandler.java","repoName":"dbeaver","snippetEndLine":0,"snippetStartLine":0,"startLine":37,"status":"M"}],"commitId":"060fdab33fc1616fc0ff4b402b2f907c5060695d","commitMessage":"@@@#7444 PG restore + script execute tasks\n\n\nFormer-commit-id: de68125fb5527d45fc69365a262cb5811914a5bd","date":"2019-12-22 03:28:45","modifiedFileCount":"11","status":"M","submitter":"Serge Rider"}]
